gnum/__init__.py
gnum/gnumint_mod.py
gnum-0.0.1.dist-info/METADATA
gnum-0.0.1.dist-info/WHEEL
gnum-0.0.1.dist-info/top_level.txt
gnum-0.0.1.dist-info/RECORD
