Metadata-Version: 2.1
Name: gnum
Version: 0.0.1
Summary: Generates random number from given max value
Author: Myzerfist
Keywords: python,random,random number
Classifier: Development Status :: 1 - Planning
Classifier: Intended Audience :: Developers
Classifier: Programming Language :: Python :: 3
Classifier: Operating System :: Unix
Classifier: Operating System :: MacOS :: MacOS X
Classifier: Operating System :: Microsoft :: Windows
